parthial/__init__.py
parthial/built_ins.py
parthial/context.py
parthial/errs.py
parthial/serialize.py
parthial/vals.py
parthial-0.2.2.dist-info/DESCRIPTION.rst
parthial-0.2.2.dist-info/METADATA
parthial-0.2.2.dist-info/RECORD
parthial-0.2.2.dist-info/WHEEL
parthial-0.2.2.dist-info/metadata.json
parthial-0.2.2.dist-info/top_level.txt
parthial-0.2.2.dist-info/zip-safe
