Metadata-Version: 2.0
Name: parthial
Version: 0.2.2
Summary: Lisp interpreter for user-scriptable server-side applications
Home-page: https://github.com/benzrf/parthial
Author: benzrf
Author-email: benzrf@benzrf.com
License: GPLv3
Platform: any
Classifier: Development Status :: 2 - Pre-Alpha
Classifier: Intended Audience :: Developers
Classifier: License :: OSI Approved :: GNU General Public License v3 (GPLv3)
Classifier: Operating System :: OS Independent
Classifier: Programming Language :: Lisp
Classifier: Programming Language :: Python :: 3.3
Classifier: Programming Language :: Python :: 3.4
Classifier: Programming Language :: Python :: 3.5
Classifier: Programming Language :: Python :: 3 :: Only
Classifier: Topic :: Software Development :: Interpreters
Requires-Dist: pyyaml
